aiofluent/__init__.py
aiofluent/event.py
aiofluent/handler.py
aiofluent/sender.py
aiofluent-1.2.8.dist-info/COPYING
aiofluent-1.2.8.dist-info/METADATA
aiofluent-1.2.8.dist-info/WHEEL
aiofluent-1.2.8.dist-info/top_level.txt
aiofluent-1.2.8.dist-info/RECORD
