Metadata-Version: 2.1
Name: aiofluent
Version: 1.2.8
Summary: A Python logging handler for Fluentd event collector
Home-page: https://github.com/guillotinaweb/aiofluent
Author: Nathan Van Gheem
Author-email: vangheem@gmail.com
License: Apache License, Version 2.0
Download-URL: http://pypi.python.org/pypi/aiofluent/
Platform: UNKNOWN
Classifier: Programming Language :: Python :: 3
Classifier: Development Status :: 4 - Beta
Classifier: Intended Audience :: Developers
Requires-Dist: msgpack-python
Provides-Extra: test
Requires-Dist: pytest (>=3.8.0) ; extra == 'test'
Requires-Dist: pytest-asyncio (>=0.10.0) ; extra == 'test'
Requires-Dist: pytest-cov ; extra == 'test'
Requires-Dist: coverage (>=4.0.3) ; extra == 'test'
